swarmauri_experimental/RemoteUniversalBase.py
swarmauri_experimental/__init__.py
swarmauri_experimental/apis/CeleryAgentCommands.py
swarmauri_experimental/apis/README.md
swarmauri_experimental/chains/IChainFormatter.py
swarmauri_experimental/chains/IChainNotification.py
swarmauri_experimental/chains/IChainPersistence.py
swarmauri_experimental/chains/IChainScheduler.py
swarmauri_experimental/chains/TypeAgnosticCallableChain.py
swarmauri_experimental/chains/__init__.py
swarmauri_experimental/conversations/ConsensusBuildingConversation.md
swarmauri_experimental/conversations/ConsensusBuildingConversation.py
swarmauri_experimental/conversations/SemanticConversation.py
swarmauri_experimental/conversations/SharedConversation.py
swarmauri_experimental/conversations/__init__.py
swarmauri_experimental/distances/SSASimilarity.py
swarmauri_experimental/distances/SSIVSimilarity.py
swarmauri_experimental/distances/__init__.py
swarmauri_experimental/docs/replay.md
swarmauri_experimental/document_stores/TriplesDocumentStore.py
swarmauri_experimental/document_stores/Word2VecDocumentStore.py
swarmauri_experimental/document_stores/__init__.py
swarmauri_experimental/embeddings/SpatialDocEmbedding.py
swarmauri_experimental/embeddings/__init__.py
swarmauri_experimental/llms/OpenRouterModel.py
swarmauri_experimental/llms/ShuttleAIImgGenModel.py
swarmauri_experimental/llms/ShuttleAIModel.py
swarmauri_experimental/llms/ShuttleAIToolModel.py
swarmauri_experimental/llms/__init__.py
swarmauri_experimental/models/HierarchicalAttentionModel.py
swarmauri_experimental/models/SageMaker.py
swarmauri_experimental/models/__init__.py
swarmauri_experimental/parsers/PDFToTextParser.py
swarmauri_experimental/parsers/__init__.py
swarmauri_experimental/tools/CypherQueryTool.py
swarmauri_experimental/tools/FileDownloaderTool.py
swarmauri_experimental/tools/LinkedInArticleTool.py
swarmauri_experimental/tools/OutlookSendMailTool.py
swarmauri_experimental/tools/PaCMAPTool.py
swarmauri_experimental-0.6.0.dev26.dist-info/METADATA
swarmauri_experimental-0.6.0.dev26.dist-info/WHEEL
swarmauri_experimental-0.6.0.dev26.dist-info/RECORD
